beeai_sdk/__init__.py
beeai_sdk/a2a/__init__.py
beeai_sdk/a2a/extensions/__init__.py
beeai_sdk/a2a/extensions/auth/__init__.py
beeai_sdk/a2a/extensions/auth/oauth/__init__.py
beeai_sdk/a2a/extensions/auth/oauth/oauth.py
beeai_sdk/a2a/extensions/auth/oauth/storage/__init__.py
beeai_sdk/a2a/extensions/auth/oauth/storage/base.py
beeai_sdk/a2a/extensions/auth/oauth/storage/memory.py
beeai_sdk/a2a/extensions/auth/secrets/__init__.py
beeai_sdk/a2a/extensions/auth/secrets/secrets.py
beeai_sdk/a2a/extensions/base.py
beeai_sdk/a2a/extensions/exceptions.py
beeai_sdk/a2a/extensions/services/__init__.py
beeai_sdk/a2a/extensions/services/embedding.py
beeai_sdk/a2a/extensions/services/llm.py
beeai_sdk/a2a/extensions/services/mcp.py
beeai_sdk/a2a/extensions/services/platform.py
beeai_sdk/a2a/extensions/ui/__init__.py
beeai_sdk/a2a/extensions/ui/agent_detail.py
beeai_sdk/a2a/extensions/ui/canvas.py
beeai_sdk/a2a/extensions/ui/citation.py
beeai_sdk/a2a/extensions/ui/form.py
beeai_sdk/a2a/extensions/ui/settings.py
beeai_sdk/a2a/extensions/ui/trajectory.py
beeai_sdk/a2a/types.py
beeai_sdk/platform/__init__.py
beeai_sdk/platform/client.py
beeai_sdk/platform/common.py
beeai_sdk/platform/configuration.py
beeai_sdk/platform/context.py
beeai_sdk/platform/file.py
beeai_sdk/platform/model_provider.py
beeai_sdk/platform/provider.py
beeai_sdk/platform/provider_build.py
beeai_sdk/platform/types.py
beeai_sdk/platform/variables.py
beeai_sdk/platform/vector_store.py
beeai_sdk/py.typed
beeai_sdk/server/__init__.py
beeai_sdk/server/agent.py
beeai_sdk/server/app.py
beeai_sdk/server/constants.py
beeai_sdk/server/context.py
beeai_sdk/server/dependencies.py
beeai_sdk/server/logging.py
beeai_sdk/server/server.py
beeai_sdk/server/store/__init__.py
beeai_sdk/server/store/context_store.py
beeai_sdk/server/store/memory_context_store.py
beeai_sdk/server/store/platform_context_store.py
beeai_sdk/server/telemetry.py
beeai_sdk/server/utils.py
beeai_sdk/util/__init__.py
beeai_sdk/util/file.py
beeai_sdk-0.3.7.dist-info/WHEEL
beeai_sdk-0.3.7.dist-info/METADATA
beeai_sdk-0.3.7.dist-info/RECORD
